pyadf/__init__.py
pyadf/_logger.py
pyadf/document.py
pyadf/exceptions.py
pyadf/markdown.py
pyadf/nodes.py
pyadf-0.3.0.dist-info/licenses/LICENSE
pyadf-0.3.0.dist-info/METADATA
pyadf-0.3.0.dist-info/WHEEL
pyadf-0.3.0.dist-info/top_level.txt
pyadf-0.3.0.dist-info/RECORD
