Metadata-Version: 2.4
Name: pyadf
Version: 0.3.0
Summary: A Python library for converting Atlassian Document Format (ADF) to Markdown
Author-email: Youngseok Choi <me@youngseok.com>
License-Expression: MIT
Project-URL: Homepage, https://github.com/YoungseokCh/pyadf
Project-URL: Repository, https://github.com/YoungseokCh/pyadf
Project-URL: Issues, https://github.com/YoungseokCh/pyadf/issues
Keywords: adf,markdown,atlassian,converter,confluence,jira
Classifier: Development Status :: 3 - Alpha
Classifier: Intended Audience :: Developers
Classifier: Programming Language :: Python :: 3
Classifier: Programming Language :: Python :: 3.11
Classifier: Programming Language :: Python :: 3.12
Classifier: Programming Language :: Python :: 3.13
Classifier: Topic :: Text Processing :: Markup
Requires-Python: >=3.11
License-File: LICENSE
Dynamic: license-file
